rnd_customtools/__init__.py
rnd_customtools/tools/__init__.py
rnd_customtools/tools/aif_llm_tool.py
rnd_customtools/tools/utils.py
rnd_customtools/yamls/aif_llm_tool.yaml
tests/__init__.py
tests/test_aif_llm_tool.py
rnd_customtools-0.0.2.dist-info/METADATA
rnd_customtools-0.0.2.dist-info/WHEEL
rnd_customtools-0.0.2.dist-info/entry_points.txt
rnd_customtools-0.0.2.dist-info/top_level.txt
rnd_customtools-0.0.2.dist-info/RECORD
