Metadata-Version: 2.1
Name: rnd-customtools
Version: 0.0.2
Summary: This is my tools package
